JSON4JSON/JSON4JSON.py
JSON4JSON/__init__.py
JSON4JSON/utils.py
JSON4JSON/DataTypes/DefaultTypes.py
JSON4JSON/DataTypes/__init__.py
JSON4JSON/DataTypes/basics.py
JSON4JSON/DataTypes/dictType.py
JSON4JSON/DataTypes/extended.py
JSON4JSON/DataTypes/units.py
JSON4JSON/VarTypes/DefaultVarTypes.py
JSON4JSON/VarTypes/__init__.py
JSON4JSON/VarTypes/basicVarTypes.py
JSON4JSON-0.4.3.dist-info/LICENSE
JSON4JSON-0.4.3.dist-info/METADATA
JSON4JSON-0.4.3.dist-info/WHEEL
JSON4JSON-0.4.3.dist-info/top_level.txt
JSON4JSON-0.4.3.dist-info/RECORD
