Metadata-Version: 2.1
Name: JSON4JSON
Version: 0.4.3
Summary: Configure JSON with JSON
Home-page: https://github.com/TrevorBagels/JSON4JSON
Author: Trevor Bagels
Author-email: trevorbagels@gmail.com
License: GNU GPLv3
Platform: UNKNOWN
Classifier: License :: OSI Approved :: GNU General Public License v3 or later (GPLv3+)
Classifier: Programming Language :: Python :: 3
Classifier: Programming Language :: Python :: 3.7
